scarfs/__init__.py
scarfs-0.1.1.dist-info/LICENSE
scarfs-0.1.1.dist-info/WHEEL
scarfs-0.1.1.dist-info/METADATA
scarfs-0.1.1.dist-info/RECORD
